zap_cdk/__init__.py
zap_cdk/py.typed
zap_cdk/_jsii/__init__.py
zap_cdk/_jsii/zap-cdk@0.0.11.jsii.tgz
zap_cdk-0.0.11.dist-info/LICENSE
zap_cdk-0.0.11.dist-info/METADATA
zap_cdk-0.0.11.dist-info/WHEEL
zap_cdk-0.0.11.dist-info/top_level.txt
zap_cdk-0.0.11.dist-info/RECORD
